fulltmdb/__init__.py
fulltmdb/base.py
fulltmdb/v3/__init__.py
fulltmdb/v3/accounts.py
fulltmdb/v3/authentication.py
fulltmdb/v3/certifications.py
fulltmdb/v3/changes.py
fulltmdb/v3/collections.py
fulltmdb/v3/companies.py
fulltmdb/v3/configuration.py
fulltmdb/v3/credits.py
fulltmdb/v3/discover.py
fulltmdb/v3/episode_groups.py
fulltmdb/v3/episodes.py
fulltmdb/v3/find.py
fulltmdb/v3/genres.py
fulltmdb/v3/guests.py
fulltmdb/v3/keywords.py
fulltmdb/v3/lists.py
fulltmdb/v3/movies.py
fulltmdb/v3/networks.py
fulltmdb/v3/people.py
fulltmdb/v3/providers.py
fulltmdb/v3/reviews.py
fulltmdb/v3/search.py
fulltmdb/v3/seasons.py
fulltmdb/v3/trending.py
fulltmdb/v3/tv.py
fulltmdb/v4/__init__.py
fulltmdb/v4/accounts.py
fulltmdb/v4/auth.py
fulltmdb/v4/lists.py
fulltmdb-0.3.0.dist-info/LICENSE
fulltmdb-0.3.0.dist-info/METADATA
fulltmdb-0.3.0.dist-info/WHEEL
fulltmdb-0.3.0.dist-info/top_level.txt
fulltmdb-0.3.0.dist-info/RECORD
