Metadata-Version: 2.1
Name: fulltmdb
Version: 0.3.0
Summary: A wrapper for The Movie Database API v3 and v4.
Home-page: https://github.com/Jacob212/fulltmdb
Author: Jacob Hale
Author-email: jacobhale.hale@gmail.com
License: UNKNOWN
Keywords: tmdb,api-wrapper
Platform: UNKNOWN
Classifier: Development Status :: 4 - Beta
Classifier: Intended Audience :: Developers
Classifier: Operating System :: OS Independent
Classifier: Programming Language :: Python
Classifier: Programming Language :: Python :: 3.6
Classifier: Programming Language :: Python :: 3.7
Classifier: Programming Language :: Python :: 3.8
Classifier: Programming Language :: Python :: 3.9
Classifier: Topic :: Utilities
License-File: LICENSE
Requires-Dist: requests
Requires-Dist: requests-cache
